quackosm-0.16.3.dist-info/METADATA
quackosm-0.16.3.dist-info/WHEEL
quackosm-0.16.3.dist-info/entry_points.txt
quackosm-0.16.3.dist-info/licenses/LICENSE
quackosm/__init__.py
quackosm/__main__.py
quackosm/_constants.py
quackosm/_exceptions.py
quackosm/_geohash_parser.py
quackosm/_geoparquet_metadata.py
quackosm/_intersection.py
quackosm/_osm_tags_filters.py
quackosm/_osm_way_polygon_features.py
quackosm/_parquet_multiprocessing.py
quackosm/_rich_progress.py
quackosm/_typing.py
quackosm/cli.py
quackosm/functions.py
quackosm/geocode.py
quackosm/osm_extracts/__init__.py
quackosm/osm_extracts/_poly_parser.py
quackosm/osm_extracts/bbbike.py
quackosm/osm_extracts/extract.py
quackosm/osm_extracts/extracts_tree.py
quackosm/osm_extracts/geofabrik.py
quackosm/osm_extracts/osm_fr.py
quackosm/osm_way_polygon_features.json
quackosm/pbf_file_reader.py
quackosm/py.typed
quackosm-0.16.3.dist-info/RECORD
