Metadata-Version: 2.1
Name: QuackOSM
Version: 0.16.3
Summary: An open-source tool for reading OpenStreetMap PBF files using DuckDB
Author-Email: Kamil Raczycki <kraczycki@kraina.ai>
License: Apache-2.0
Classifier: Development Status :: 3 - Alpha
Classifier: License :: OSI Approved :: Apache Software License
Classifier: Topic :: Scientific/Engineering :: Artificial Intelligence
Classifier: Topic :: Scientific/Engineering :: GIS
Classifier: Intended Audience :: Science/Research
Classifier: Intended Audience :: Developers
Classifier: Programming Language :: Python :: 3
Classifier: Programming Language :: Python :: 3.9
Classifier: Programming Language :: Python :: 3.10
Classifier: Programming Language :: Python :: 3.11
Classifier: Programming Language :: Python :: 3.12
Classifier: Programming Language :: Python :: 3.13
Classifier: Operating System :: Unix
Classifier: Operating System :: MacOS
Classifier: Operating System :: Microsoft :: Windows
Project-URL: Homepage, https://kraina-ai.github.io/quackosm
Project-URL: Repository, https://github.com/kraina-ai/quackosm
Project-URL: Documentation, https://kraina-ai.github.io/quackosm
Project-URL: Changelog, https://github.com/kraina-ai/quackosm/blob/main/CHANGELOG.md
Requires-Python: >=3.9
Requires-Dist: geopandas>=0.6
Requires-Dist: shapely>=2
Requires-Dist: pyarrow>=16.0.0
Requires-Dist: duckdb>=1.1.2
Requires-Dist: geoarrow-pyarrow>=0.1.2
Requires-Dist: typeguard>=3.0.0
Requires-Dist: psutil>=5.6.2
Requires-Dist: pooch>=1.6.0
Requires-Dist: tqdm>=4.42.0
Requires-Dist: beautifulsoup4
Requires-Dist: requests
Requires-Dist: rich>=12.0.0
Requires-Dist: geopy>=2.0.0
Requires-Dist: numpy>=1.26.0
Requires-Dist: rq_geo_toolkit>=2025.8.3
Provides-Extra: cli
Requires-Dist: typer[all]>=0.9.0; extra == "cli"
Requires-Dist: s2sphere>=0.2.5; extra == "cli"
